pyprocessors_consolidate/__init__.py
pyprocessors_consolidate/consolidate.py
pyprocessors_consolidate-0.5.194.dist-info/entry_points.txt
pyprocessors_consolidate-0.5.194.dist-info/licenses/LICENSE
pyprocessors_consolidate-0.5.194.dist-info/WHEEL
pyprocessors_consolidate-0.5.194.dist-info/METADATA
pyprocessors_consolidate-0.5.194.dist-info/RECORD
